{
    "ID": "bruce_open_1_3",
    "marked": "Fully",
    "unitName": "open",
    "unitCode": "open",
    "time": "05/25/2020, 00:21:24",
    "user": "bruce",
    "questionset": "open_1",
    "totalAvailmarks": 10,
    "autoMarksachieved": 0,
    "manualMarksachieved": 6,
    "availAutomarks": 0,
    "incorrectAutoquestions": [],
    "youAnswered": [],
    "correctAnswers": [],
    "requireManual": [
        "11",
        "1",
        "1",
        "1",
        "1",
        "1",
        "1",
        "1",
        "1",
        "11111"
    ],
    "manualAnswers": [
        "Sample Response",
        "Sample Response",
        "Sample Response",
        "Sample Response",
        "Sample Response",
        "Sample Response",
        "Sample Response",
        "Sample Response",
        "Sample Response",
        "Sample Response"
    ],
    "availManualMarks": [
        1,
        1,
        1,
        1,
        1,
        1,
        1,
        1,
        1,
        1
    ],
    "manualMarks": [
        1,
        0,
        0,
        0,
        0,
        1,
        1,
        1,
        1,
        1
    ]
}